odoo/addons/html_image_url_extractor/README.rst
odoo/addons/html_image_url_extractor/__init__.py
odoo/addons/html_image_url_extractor/__manifest__.py
odoo/addons/html_image_url_extractor/i18n/am.po
odoo/addons/html_image_url_extractor/i18n/ar.po
odoo/addons/html_image_url_extractor/i18n/bg.po
odoo/addons/html_image_url_extractor/i18n/bs.po
odoo/addons/html_image_url_extractor/i18n/ca.po
odoo/addons/html_image_url_extractor/i18n/cs.po
odoo/addons/html_image_url_extractor/i18n/cs_CZ.po
odoo/addons/html_image_url_extractor/i18n/da.po
odoo/addons/html_image_url_extractor/i18n/de.po
odoo/addons/html_image_url_extractor/i18n/el_GR.po
odoo/addons/html_image_url_extractor/i18n/en_GB.po
odoo/addons/html_image_url_extractor/i18n/es.po
odoo/addons/html_image_url_extractor/i18n/es_AR.po
odoo/addons/html_image_url_extractor/i18n/es_CL.po
odoo/addons/html_image_url_extractor/i18n/es_CO.po
odoo/addons/html_image_url_extractor/i18n/es_CR.po
odoo/addons/html_image_url_extractor/i18n/es_DO.po
odoo/addons/html_image_url_extractor/i18n/es_EC.po
odoo/addons/html_image_url_extractor/i18n/es_ES.po
odoo/addons/html_image_url_extractor/i18n/es_MX.po
odoo/addons/html_image_url_extractor/i18n/es_PE.po
odoo/addons/html_image_url_extractor/i18n/es_PY.po
odoo/addons/html_image_url_extractor/i18n/es_VE.po
odoo/addons/html_image_url_extractor/i18n/et.po
odoo/addons/html_image_url_extractor/i18n/eu.po
odoo/addons/html_image_url_extractor/i18n/fa.po
odoo/addons/html_image_url_extractor/i18n/fi.po
odoo/addons/html_image_url_extractor/i18n/fr.po
odoo/addons/html_image_url_extractor/i18n/fr_CA.po
odoo/addons/html_image_url_extractor/i18n/fr_CH.po
odoo/addons/html_image_url_extractor/i18n/gl.po
odoo/addons/html_image_url_extractor/i18n/he.po
odoo/addons/html_image_url_extractor/i18n/hr.po
odoo/addons/html_image_url_extractor/i18n/hr_HR.po
odoo/addons/html_image_url_extractor/i18n/html_image_url_extractor.pot
odoo/addons/html_image_url_extractor/i18n/hu.po
odoo/addons/html_image_url_extractor/i18n/id.po
odoo12_addon_html_image_url_extractor-12.0.1.0.0.99.dev8.dist-info/METADATA
odoo12_addon_html_image_url_extractor-12.0.1.0.0.99.dev8.dist-info/WHEEL
odoo12_addon_html_image_url_extractor-12.0.1.0.0.99.dev8.dist-info/top_level.txt
odoo12_addon_html_image_url_extractor-12.0.1.0.0.99.dev8.dist-info/RECORD
